Workbook

Sheet Signings
B1: brought forward | C1: 45748 | D1: =EOMONTH(C1,1) -> 45808 | E1: =EOMONTH(D1,1) -> 45838 | F1: =EOMONTH(E1,1) -> 45869 | G1: =EOMONTH(F1,1) -> 45900 | H1: =EOMONTH(G1,1) -> 45930 | I1: =EOMONTH(H1,1) -> 45961 | J1: =EOMONTH(I1,1) -> 45991 | K1: =EOMONTH(J1,1) -> 46022 | ... P1: =EOMONTH(O1,1) -> 46173 | Q1: Total
A2: OLIVE
A3: Total Keys | B3: 2389 | C3: 43 | D3: 92 | E3: 27 | F3: 110 | G3: 42 | H3: 30 | I3: 45 | J3: 90 | K3: 60 | L3: 61 | M3: 135 | N3: 111 | O3: 0 | P3: 30 | Q3: =SUM(B3:P3) -> 3265
A4: Total Properties | B4: 54 | C4: 1 | D4: 2 | E4: 1 | F4: 3 | G4: 1 | H4: 1 | I4: 1 | J4: 2 | K4: 2 | L4: 1 | M4: 4 | N4: 3 | O4: =I29 -> 1 | P4: 1 | Q4: =SUM(B4:P4) -> 78
A5: Olive Cumulative Properties | B5: =B4 -> 54 | C5: =C4+B4 -> 55 | D5: =C5+D4 -> 57 | E5: =D5+E4 -> 58 | F5: =E5+F4 -> 61 | G5: =F5+G4 -> 62 | H5: =G5+H4 -> 63 | I5: =H5+I4 -> 64 | J5: =I5+J4 -> 66 | K5: =J5+K4 -> 68 | ... P5: =O5+P4 -> 78 | Q5: =Q4-P5 -> 0
A6: Olive Cumulative keys | B6: =B3 -> 2389 | C6: =B6+C3 -> 2432 | D6: =C6+D3 -> 2524 | E6: =D6+E3 -> 2551 | F6: =E6+F3 -> 2661 | G6: =F6+G3 -> 2703 | H6: =G6+H3 -> 2733 | I6: =H6+I3 -> 2778 | J6: =I6+J3 -> 2868 | ... P6: =O6+P3 -> 3265 | Q6: =P6-Q3 -> 0
A7: SPARK
A8: Total Keys | B8: 528 | D8: 228 | E8: 90 | F8: 175 | G8: 55 | H8: 90 | I8: 119 | J8: 40 | K8: 338 | L8: 316 | M8: 51 | N8: 227 | O8: 0 | P8: 60 | Q8: =SUM(B8:P8) -> 2317
A9: Total Properties | B9: 6 | C9: 0 | D9: 3 | E9: 1 | F9: 2 | G9: 1 | H9: 1 | I9: 2 | J9: 1 | K9: 3 | L9: 3 | M9: 1 | N9: 4 | O9: =I30 -> 1 | P9: 1 | Q9: =SUM(B9:P9) -> 30
A10: Spark Cumulative properties | B10: =B9 -> 6 | C10: =C9+B9 -> 6 | D10: =C10+D9 -> 9 | E10: =D10+E9 -> 10 | F10: =E10+F9 -> 12 | G10: =F10+G9 -> 13 | H10: =G10+H9 -> 14 | I10: =H10+I9 -> 16 | J10: =I10+J9 -> 17 | K10: =J10+K9 -> 20 | ... P10: =O10+P9 -> 30 | Q10: =Q9-P10 -> 0
A11: Spark Cumulative keys | B11: =B8 -> 528 | C11: =B11+C8 -> 528 | D11: =C11+D8 -> 756 | E11: =D11+E8 -> 846 | F11: =E11+F8 -> 1021 | G11: =F11+G8 -> 1076 | H11: =G11+H8 -> 1166 | I11: =H11+I8 -> 1285 | J11: =I11+J8 -> 1325 | ... P11: =O11+P8 -> 2317 | Q11: =Q8-P11 -> 0
A12: OPEN
A13: Total Keys | B13: 116 | C13: 104 | D13: 90 | E13: 40 | F13: 28 | G13: 0 | H13: 68 | I13: 43 | J13: 61 | K13: 14 | L13: 135 | M13: 152 | N13: 196 | O13: 268 | P13: 0 | Q13: =SUM(B13:P13) -> 1315
A14: Total Properties | B14: 4 | C14: 3 | D14: 2 | E14: 1 | F14: 1 | G14: 0 | H14: 2 | I14: 2 | J14: 3 | K14: 1 | L14: 4 | M14: 8 | N14: 9 | O14: 7 | P14: 0 | Q14: =SUM(B14:P14) -> 47
A15: Open Cumulative properties | B15: =B14 -> 4 | C15: =C14+B14 -> 7 | D15: =C15+D14 -> 9 | E15: =D15+E14 -> 10 | F15: =E15+F14 -> 11 | G15: =F15+G14 -> 11 | H15: =G15+H14 -> 13 | I15: =H15+I14 -> 15 | J15: =I15+J14 -> 18 | K15: =J15+K14 -> 19 | ... P15: =O15+P14 -> 47 | Q15: =Q14-O15 -> 0
A16: Open Cumulative keys | B16: =B13 -> 116 | C16: =B16+C13 -> 220 | D16: =C16+D13 -> 310 | E16: =D16+E13 -> 350 | F16: =E16+F13 -> 378 | G16: =F16+G13 -> 378 | H16: =G16+H13 -> 446 | I16: =H16+I13 -> 489 | J16: =I16+J13 -> 550 | ... P16: =O16+P13 -> 1315 | Q16: =Q13-O16 -> 0
A17: Overall
A18: Total properties | B18: =B4+B9+B14 -> 64 | C18: =C4+C9+C14 -> 4 | D18: =D4+D9+D14 -> 7 | E18: =E4+E9+E14 -> 3 | F18: =F4+F9+F14 -> 6 | G18: =G4+G9+G14 -> 2 | H18: =H4+H9+H14 -> 4 | I18: =I4+I9+I14 -> 5 | ... Q18: =Q4+Q9+Q14 -> 155
A19: Total keys | B19: =B3+B8+B13 -> 3033 | C19: =C3+C8+C13 -> 147 | D19: =D3+D8+D13 -> 410 | E19: =E3+E8+E13 -> 157 | F19: =F3+F8+F13 -> 313 | G19: =G3+G8+G13 -> 97 | H19: =H3+H8+H13 -> 188 | I19: =I3+I8+I13 -> 207 | ... Q19: =Q3+Q8+Q13 -> 6897
A20: Overall Cumulative properties | B20: =B18 -> 64 | C20: =C18+B20 -> 68 | D20: =D18+C20 -> 75 | E20: =E18+D20 -> 78 | F20: =F18+E20 -> 84 | G20: =G18+F20 -> 86 | H20: =H18+G20 -> 90 | I20: =I18+H20 -> 95 | J20: =J18+I20 -> 101 | ... P20: =P18+O20 -> 155 | Q20: =Q18-P20 -> 0
A21: Overall Cumulative keys | B21: =B19 -> 3033 | C21: =C19+B21 -> 3180 | D21: =D19+C21 -> 3590 | E21: =E19+D21 -> 3747 | F21: =F19+E21 -> 4060 | G21: =G19+F21 -> 4157 | H21: =H19+G21 -> 4345 | I21: =I19+H21 -> 4552 | J21: =J19+I21 -> 4743 | ... P21: =P19+O21 -> 6897 | Q21: =Q19-P21 -> 0
D25: May '26
B26: March '26 | C26: April '26 | D26: Week 1 | E26: Week 2 | F26: Week 3 | G26: Week 4 | H26: Week 5 | I26: Total
A27: Brands
A28: Open | B28: 9 | C28: 7 | D28: 0 | I28: =SUM(D28:H28) -> 0
A29: Olive | B29: 3 | C29: 0 | D29: 1 | I29: =SUM(D29:H29) -> 1
A30: Spark | B30: 4 | C30: 2 | D30: 1 | I30: =SUM(D30:H30) -> 1
A33: Portfolio Update:
A34: 1. Olive Brand:
A35: Dehradun (MA) : 30 keys
A37: 2. Spark
A38: Thane (LOI) : 60 keys

Sheet Operational
I1: Operational
C3: brought forwrad | D3: 45748 | E3: =EOMONTH(D3,1) -> 45808 | F3: =EOMONTH(E3,1) -> 45838 | G3: =EOMONTH(F3,1) -> 45869 | H3: =EOMONTH(G3,1) -> 45900 | I3: =EOMONTH(H3,1) -> 45930 | J3: =EOMONTH(I3,1) -> 45961 | K3: =EOMONTH(J3,1) -> 45991 | L3: =EOMONTH(K3,1) -> 46022 | ... Q3: =EOMONTH(P3,1) -> 46173 | R3: Total
B4: OLIVE
B5: Total Keys | C5: 1232 | D5: 0 | E5: 0 | F5: 90 | G5: 0 | H5: 0 | I5: 86 | J5: 0 | K5: 73 | L5: 40 | M5: 123 | O5: 56 | P5: 0 | Q5: 0 | R5: =SUM(C5:Q5) -> 1700
B6: Total Properties | C6: 32 | D6: 0 | E6: 0 | F6: 2 | G6: 0 | H6: 0 | I6: 1 | J6: 0 | K6: 1 | L6: 1 | M6: 3 | O6: 1 | P6: 0 | Q6: 0 | R6: =SUM(C6:O6) -> 41
B7: Olive Cumulative keys | C7: =C5 -> 1232 | D7: =C7+D5 -> 1232 | E7: =D7+E5 -> 1232 | F7: =E7+F5 -> 1322 | G7: =F7+G5 -> 1322 | H7: =G7+H5 -> 1322 | I7: =H7+I5 -> 1408 | J7: =I7+J5 -> 1408 | K7: =J7+K5 -> 1481 | ... Q7: =P7+Q5 -> 1700 | R7: =R5-O7 -> 0
B8: Olive Cumulative Properties | C8: =C6 -> 32 | D8: =D6+C8 -> 32 | E8: =E6+D8 -> 32 | F8: =F6+E8 -> 34 | G8: =G6+F8 -> 34 | H8: =H6+G8 -> 34 | I8: =I6+H8 -> 35 | J8: =J6+I8 -> 35 | K8: =K6+J8 -> 36 | ... Q8: =Q6+P8 -> 41 | R8: =R6-O8 -> 0
B9: Open
B10: Total Keys | C10: 32 | D10: 0 | E10: 73 | F10: 26 | G10: 112 | H10: 30 | I10: 28 | J10: 51 | K10: 78 | L10: 20 | M10: 60 | N10: 0 | O10: 143 | P10: =15+24+25+27 -> 91 | Q10: 0 | R10: =SUM(C10:Q10) -> 744 | S10: =R5+R10 -> 2444
B11: Total Properties | C11: 1 | D11: 0 | E11: 2 | F11: 1 | G11: 2 | H11: 1 | I11: 1 | J11: 2 | K11: 3 | L11: 1 | M11: 2 | N11: 0 | O11: 5 | P11: 4 | Q11: 0 | R11: =SUM(C11:Q11) -> 25
B12: Open Cumulative Keys | C12: =C10 -> 32 | D12: =C12+D10 -> 32 | E12: =D12+E10 -> 105 | F12: =E12+F10 -> 131 | G12: =F12+G10 -> 243 | H12: =G12+H10 -> 273 | I12: =H12+I10 -> 301 | J12: =I12+J10 -> 352 | K12: =J12+K10 -> 430 | ... Q12: =P12+Q10 -> 744 | R12: =R10-P12 -> 0
B13: Open Cumulative Properties | C13: =C11 -> 1 | D13: =D11+C13 -> 1 | E13: =E11+D13 -> 3 | F13: =F11+E13 -> 4 | G13: =G11+F13 -> 6 | H13: =H11+G13 -> 7 | I13: =I11+H13 -> 8 | J13: =J11+I13 -> 10 | K13: =K11+J13 -> 13 | ... O13: =O11+N13 -> 21 | P13: =O13+P11 -> 25 | Q13: =P13+Q11 -> 25 | R13: =R11-P13 -> 0
B14: Overall
B15: Total Keys | C15: =C5+C10 -> 1264 | D15: =D5+D10 -> 0 | E15: =E5+E10 -> 73 | F15: =F5+F10 -> 116 | G15: =G5+G10 -> 112 | H15: =H5+H10 -> 30 | I15: =I5+I10 -> 114 | J15: =J5+J10 -> 51 | ... Q15: =Q5+Q10 -> 0 | R15: =SUM(C15:P15) -> 2444
B16: Total Properties | C16: =C8+C13 -> 33 | D16: =D6+D11 -> 0 | E16: =E6+E11 -> 2 | F16: =F6+F11 -> 3 | G16: =G6+G11 -> 2 | H16: =H6+H11 -> 1 | I16: =I6+I11 -> 2 | J16: =J6+J11 -> 2 | K16: =K6+K11 -> 4 | ... Q16: =Q6+Q11 -> 0 | R16: =SUM(C16:P16) -> 66 | S16: =SUM(D16:O16) -> 29
B17: Overall Cumulative Keys | C17: =C15 -> 1264 | D17: =C17+D15 -> 1264 | E17: =D17+E15 -> 1337 | F17: =E17+F15 -> 1453 | G17: =F17+G15 -> 1565 | H17: =G17+H15 -> 1595 | I17: =H17+I15 -> 1709 | J17: =I17+J15 -> 1760 | K17: =J17+K15 -> 1911 | ... Q17: =P17+Q15 -> 2444 | R17: =R15-P17 -> 0
B18: Overall Cumulative Properties | C18: =C16 -> 33 | D18: =C18+D16 -> 33 | E18: =D18+E16 -> 35 | F18: =E18+F16 -> 38 | G18: =F18+G16 -> 40 | H18: =G18+H16 -> 41 | I18: =H18+I16 -> 43 | J18: =I18+J16 -> 45 | K18: =J18+K16 -> 49 | ... Q18: =P18+Q16 -> 66 | R18: =R16-P18 -> 0
E19: May '26
C20: March'26 | D20: April '26 | E20: Week 1 | F20: Week 2 | G20: Week 3 | H20: Week 4 | I20: Week 5 | J20: Total
B21: Brands
B22: Open
B23: -Properties | C23: 5 | D23: =P11 -> 4 | J23: =SUM(F23:I23) -> 0
B24: -Keys | C24: 143 | D24: =P10 -> 91 | J24: =SUM(F24:I24) -> 0
B25: Olive | J25: =SUM(F25:I25) -> 0
B26: -Properties | C26: 1 | D26: 0 | J26: =SUM(F26:I26) -> 0
B27: -Keys | C27: 55 | D27: 0 | J27: =SUM(F27:I27) -> 0
B29: Total
B30: -Properties | C30: =C23+C26 -> 6 | D30: =SUM(D23+D26) -> 4 | J30: =SUM(F30:I30) -> 0
B31: -Keys | C31: =C24+C27 -> 198 | D31: =D27+D24 -> 91 | J31: =SUM(F31:I31) -> 0
B34: Portfolio Update: | H34: May '26 WIP | I34: Handover date | J34: Go-live date
B35: Operational Properties – NIL | H35: Hulimavu, Bangalore | I35: Monday, June15th 2026 | J35: 30th June 2026
H36: Calangute, Goa | I36: Monday, June 15th 2026 | J36: 30th June 2026
H37: Nagarjuna/Marathahalli, Bangalore | I37: Friday, June 5th 2026 | J37: 20th June 2026
H38: Nagavara, Bangalore | I38: Tuesday, May 12th 2026 | J38: 27th May 2026
H39: JP Nagar, Bangalore | I39: Monday, June15th 2026 | J39: 30th June 2026
H40: Olive Yelahanka near BMSIT BLR | I40: Friday, May 15th 2026 | J40: 30th May 2026
H41: Olive Sector 57 GUR | I41: Thursday, June 18th 2026 | J41: 3rd July 2026
H42: Vizag, AP | I42: Wednesday, May 20th 2026 | J42: 5th June 2026

Sheet Revenue
A2: 1 | C2: Property Revenue - Trend
C4: Jan '26 | D4: Feb'26 | E4: Mar'26 | F4: Apr'26 | G4: 8th May '26
B5: Long stay | C5: 4677462 | D5: 4718915 | E5: 4910464 | F5: 4983051 | G5: 1328824
B6: Short stay | C6: =C7-C5 -> 86240448 | D6: =D7-D5 -> 87243618 | E6: =E7-E5 -> 78751235 | F6: =F7-F5 -> 83033975 | G6: =G7-G5 -> 27912985
B7: Total | C7: 90917910 | D7: 91962533 | E7: 83661699 | F7: 88017026 | G7: 29241809
A10: 2 | C10: Property Revenue - vs MoM, vs YoY
C12: 8th May '25 | D12: 8th May '26 | G12: 8th April' 26 | H12: 8th May '26
B13: Long stay | C13: 1295288 | D13: 1328824 | F13: Long stay | G13: 1267216 | H13: 1328824
B14: Short stay | C14: =C15-C13 -> 15882047 | D14: =D15-D13 -> 27912985 | F14: Short stay | G14: =G15-G13 -> 19918133 | H14: =H15-H13 -> 27912985
B15: Total | C15: 17177335 | D15: 29241809 | F15: Total | G15: 21185349 | H15: 29241809
B17: Growth rate | C17: =D15/C15 -> 1.7023484 | F17: Growth rate | G17: =H15/G15 -> 1.3802845
A21: 3 | C21: Property Revenue - Online vs Offline and OTA vs OBE- 8th May '26
C23: Total | D23: Target | E23: Achievement
H24: Online | I24: %
B25: Walk-ins | C25: =C28*12% -> 3509017.1 | D25: =C25 -> 3509017.1 | E25: =C25/D25 -> 1 | G25: OBE | H25: =H28*3.5% -> 665251.15 | I25: 0.04
B26: Corporate | C26: =C28-C27-C25 -> 6725616.1 | D26: 5929032.3 | E26: =C26/D26 -> 1.1343531
B27: Online | C27: =C28*65% -> 19007176 | D27: =11836353.8064516+4175258 -> 16011612 | E27: =C27/D27 -> 1.187087 | G27: OTAs | H27: =H28-H25 -> 18341925 | I27: 0.96
C28: 29241809 | D28: =SUM(D24:D27) -> 25449661 | G28: Total | H28: =C27 -> 19007176

Sheet cashflow
B3: Cashflow - Summary
C4: April '26
C6: Target | D6: Received | J6: To be collected
B7: Inflow | D7: W1 | E7: W2 | F7: W3 | G7: W4 | H7: W5 | I7: Total
B8: TA fees | C8: =Inflow!C25 -> 6185000 | D8: =Inflow!E25 -> 820000 | E8: =Inflow!F25 -> 0 | F8: =Inflow!G25 -> 0 | G8: =Inflow!H25 -> 0 | H8: =Inflow!I25 -> 0 | I8: =SUM(D8:H8) -> 820000 | J8: =C8-I8 -> 5365000
B9: Management fees | C9: =Inflow!C27 -> 10000000 | D9: =Inflow!E27 -> 355520 | E9: =Inflow!F27 -> 0 | F9: =Inflow!G27 -> 0 | G9: =Inflow!H27 -> 0 | H9: =Inflow!I27 -> 0 | I9: =SUM(D9:H9) -> 355520 | J9: =C9-I9 -> 9644480
B10: Profit Incentive | C10: =Inflow!C29 -> 500000 | D10: =Inflow!E29 -> 0 | E10: =Inflow!F29 -> 0 | F10: =Inflow!G29 -> 0 | G10: =Inflow!H29 -> 0 | I10: =SUM(D10:G10) -> 0 | J10: =C10-I10 -> 500000
B11: Total | C11: =SUM(C8:C10) -> 16685000 | D11: =SUM(D8:D10) -> 1175520 | E11: =SUM(E8:E10) -> 0 | F11: =SUM(F8:F10) -> 0 | G11: =SUM(G8:G10) -> 0 | H11: =SUM(H8:H10) -> 0 | I11: =SUM(I8:I10) -> 1175520 | J11: =SUM(J8:J10) -> 15509480
B12: Outflow - expected (Reimbursements + Application fees + PF + TDS + GST +Sundries) | J12: =700000+2000000+3000000+2000000+1500000 -> 9200000
B15: Current bank balance | J15: =SUM(C16:C18) -> 3453737
B16: -Coliving Operations | C16: 790117
B17: - Coliving | C17: 633776
B18: -VARS | C18: 2029844
B20: Excess/Deficit (Expected outflow - current balance) | J20: =J15-J12 -> -5746263

Sheet Inflow
B4: Cashflow - Breakdown
C5: April
E6: Collections
B7: Inflow | C7: Target | E7: Received | K7: To be collected
B8: 1. TA fees | E8: W1 | F8: W2 | G8: W3 | H8: W4 | I8: W5 | J8: Total
B9: a) Spark
B10: Bengaluru - Spark - Sheshadripuram | C10: 1000000 | J10: =SUM(E10:I10) -> 0 | K10: =C10-J10 -> 1000000
B11: Spark Junagad | C11: 825000 | J11: =SUM(E11:I11) -> 0 | K11: =C11-J11 -> 825000
B12: Andheri - Le Grande | C12: 700000 | J12: =SUM(E12:I12) -> 0 | K12: =C12-J12 -> 700000 | L12: Cheque collected. Deposit date - 11/05/2026
B13: Spark Thane | C13: 500000 | E13: 500000 | J13: =SUM(E13:I13) -> 500000 | K13: =C13-J13 -> 0
B14: Spark Navsari | C14: 1500000 | J14: =SUM(E14:I14) -> 0 | K14: =C14-J14 -> 1500000 | L14: Cheque collected. Deposit date - 11/05/2026
B15: Chakan | C15: 750000 | J15: =SUM(E15:I15) -> 0 | K15: =C15-J15 -> 750000
J16: =SUM(E16:I16) -> 0 | K16: =C16-J16 -> 0
B17: b) Olive | J17: =SUM(E17:I17) -> 0 | K17: =C17-J17 -> 0
B18: Banjaara Hills | C18: 150000 | J18: =SUM(E18:I18) -> 0 | K18: =C18-J18 -> 150000
B19: Olive Bharatpur | C19: 400000 | J19: =SUM(E19:I19) -> 0 | K19: =C19-J19 -> 400000
B20: Olive Dehradun | C20: 300000 | E20: 300000 | J20: =SUM(E20:I20) -> 300000 | K20: =C20-J20 -> 0
J21: =SUM(E21:I21) -> 0 | K21: =C21-J21 -> 0
B22: c) Open set-up fees | C22: 60000 | E22: 20000 | J22: =SUM(E22:I22) -> 20000 | K22: =C22-J22 -> 40000
J23: =SUM(E23:I23) -> 0 | K23: =C23-J23 -> 0
J24: =SUM(E24:I24) -> 0 | K24: =C24-J24 -> 0
B25: Total TA fees | C25: =SUM(C10:C23) -> 6185000 | D25: =SUM(D12:D23) -> 0 | E25: =SUM(E12:E23) -> 820000 | F25: =SUM(F9:F23) -> 0 | G25: =SUM(G9:G23) -> 0 | H25: =SUM(H9:H23) -> 0 | I25: =SUM(I9:I23) -> 0 | J25: =SUM(E25:I25) -> 820000 | K25: =C25-J25 -> 5365000
K26: =C26-J26 -> 0
B27: 2. Management fees | C27: =10000000 -> 10000000 | E27: 355520 | J27: =SUM(E27:I27) -> 355520 | K27: =C27-J27 -> 9644480
K28: =C28-J28 -> 0
B29: 3. Profit Incentive | C29: 500000 | E29: 0 | J29: =SUM(E29:I29) -> 0 | K29: =C29-J29 -> 500000
K30: =C30-J30 -> 0
B31: Total Inflow | C31: =C25+C27+C29 -> 16685000 | D31: =D25+D27+D29 -> 0 | E31: =E25+E27+E29 -> 1175520 | F31: =F25+F27+F29 -> 0 | G31: =G25+G27+G29 -> 0 | H31: =H25+H27+H29 -> 0 | I31: =I25+I27+I29 -> 0 | J31: =J25+J27+J29 -> 1175520 | K31: =C31-J31 -> 15509480

Sheet workings
C5: Dairy circle | D5: 400000 | F5: -Salaries | I5: 10600000 | K5: -Salaries | N5: 11000000
C6: hitech | D6: 200000 | F6: -Car EMI | I6: 124266 | K6: -Car EMI | N6: 124266
C7: kundahalli | D7: 300000 | F7: -EE reimbursements | I7: 500000 | K7: -EE reimbursements | N7: 500000
C8: vijawada | D8: =350000*0 -> 0 | F8: -medical insurance | I8: 500000 | K8: -medical insurance | N8: 500000
C9: Vasanth nagar | D9: 350000 | F9: -OPC | I9: 2000000 | K9: -Hisca | N9: 500000
C10: Rajaji nahar | F10: -Rent | I10: 916634.45 | K10: -Zoho | N10: 361000
C11: Domlur | K11: Travel agency | N11: 500000
C12: Meera - Goa | D12: 100000 | K12: -Kingshuk | N12: 200000
C13: Indiranagar | D13: 200000 | I13: =SUM(I5:I12) -> 14640900 | N13: =SUM(N5:N12) -> 13685266
C14: Nivasa | D14: 100000
D16: =SUM(D5:D15) -> 1650000
C20: Property Name | D20: May26_Revenue(Forecast)
C21: Olive Magrath | D21: 2093438 | H21: 
C22: Olive Indiranagar | D22: 1716829 | H22: 
C23: Olive RHR | D23: 1048272 | H23: 
C24: Olive Kor 100Ft Road | D24: 677936 | H24: Task Name | I24: Hotel TYPE | J24: Status | K24: HOTO-Handover Takeover (date)
C25: Olive Kalyan Nagar | D25: 1151424 | H25: Hulimavu, Bangalore | I25: OLIVE | J25: in progress | K25: Monday, June15th 2026
C26: Olive BTM Layout | D26: 1219763 | H26: Calangute, Goa | I26: SPARK | J26: in progress | K26: Monday, June 15th 2026
C27: Olive Calangute Niwasa | D27: 630900 | H27: Nagarjuna/Marathahalli, Bangalore | I27: SPARK | J27: in progress | K27: Friday, June 5th 2026
C28: Olive Richmond Circle | D28: 998413 | H28: Nagavara, Bangalore | I28: OLIVE | J28: in progress | K28: Tuesday, May 12th 2026
C29: Olive Electronic City | D29: 1282175 | H29: JP Nagar, Bangalore | I29: OLIVE | J29: in progress | K29: Monday, June15th 2026
C30: Olive Indiranagar Metro | D30: 1282309 | H30: Olive Yelahanka near BMSIT BLR | I30: OLIVE | J30: in progress | K30: Friday, May 15th 2026
C31: Olive MG Road | D31: 1369892 | H31: Olive Sector 57 GUR | I31: OLIVE | J31: in progress | K31: Thursday, June 18th 2026
C32: Olive Calangute Mira | D32: 935767 | H32: Vizag, AP | I32: OLIVE | J32: in progress | K32: Wednesday, May 20th 2026
C33: Olive JP Nagar | D33: 1365986
C34: Olive Indiranagar 100ft Road | D34: 1381856
C35: Olive Domlur | D35: 1130166
C36: Olive Palace Road | D36: 1538423
C37: Olive Hebbal | D37: 1383608
C38: BLVD Club | D38: 412472
C39: Olive Hotel Brookefield | D39: 1470304
C40: Olive Kor 4th Block | D40: 1830048
C41: Olive Millers Road | D41: 1313716
C42: Olive Alidia Beach Resort | D42: 811961
C43: Olive Benz Circle | D43: 1682652
C44: Olive Kundalahalli | D44: 2331357
... C57: Olive Hotel Airport Road - Yelahanka by Embassy Group | D57: 387847
D59: =SUM(D21:D58) -> 45865871
D61: =D59/31*8 -> 11836354
