Workbook

Sheet Signings
B1: brought forward | C1: 45748 | D1: =EOMONTH(C1,1) -> 45808 | E1: =EOMONTH(D1,1) -> 45838 | F1: =EOMONTH(E1,1) -> 45869 | G1: =EOMONTH(F1,1) -> 45900 | H1: =EOMONTH(G1,1) -> 45930 | I1: =EOMONTH(H1,1) -> 45961 | J1: =EOMONTH(I1,1) -> 45991 | K1: =EOMONTH(J1,1) -> 46022 | ... O1: =EOMONTH(N1,1) -> 46142 | P1: Total
A2: OLIVE
A3: Total Keys | B3: 2389 | C3: 43 | D3: 92 | E3: 27 | F3: 110 | G3: 42 | H3: 30 | I3: 45 | J3: 90 | K3: 60 | L3: 61 | M3: 135 | N3: 111 | O3: 0 | P3: =SUM(B3:O3) -> 3235
A4: Total Properties | B4: 54 | C4: 1 | D4: 2 | E4: 1 | F4: 3 | G4: 1 | H4: 1 | I4: 1 | J4: 2 | K4: 2 | L4: 1 | M4: 4 | N4: 3 | O4: =H29 -> 0 | P4: =SUM(B4:O4) -> 76
A5: Olive Cumulative Properties | B5: =B4 -> 54 | C5: =C4+B4 -> 55 | D5: =C5+D4 -> 57 | E5: =D5+E4 -> 58 | F5: =E5+F4 -> 61 | G5: =F5+G4 -> 62 | H5: =G5+H4 -> 63 | I5: =H5+I4 -> 64 | J5: =I5+J4 -> 66 | K5: =J5+K4 -> 68 | ... O5: =N5+O4 -> 76 | P5: =P4-O5 -> 0
A6: Olive Cumulative keys | B6: =B3 -> 2389 | C6: =B6+C3 -> 2432 | D6: =C6+D3 -> 2524 | E6: =D6+E3 -> 2551 | F6: =E6+F3 -> 2661 | G6: =F6+G3 -> 2703 | H6: =G6+H3 -> 2733 | I6: =H6+I3 -> 2778 | J6: =I6+J3 -> 2868 | ... O6: =N6+O3 -> 3235 | P6: =P3-O6 -> 0
A7: SPARK
A8: Total Keys | B8: 528 | D8: 228 | E8: 90 | F8: 175 | G8: 55 | H8: 90 | I8: 119 | J8: 40 | K8: 338 | L8: 316 | M8: 51 | N8: 227 | O8: 0 | P8: =SUM(B8:O8) -> 2257
A9: Total Properties | B9: 6 | C9: 0 | D9: 3 | E9: 1 | F9: 2 | G9: 1 | H9: 1 | I9: 2 | J9: 1 | K9: 3 | L9: 3 | M9: 1 | N9: 4 | O9: =H30 -> 2 | P9: =SUM(B9:O9) -> 30
A10: Spark Cumulative properties | B10: =B9 -> 6 | C10: =C9+B9 -> 6 | D10: =C10+D9 -> 9 | E10: =D10+E9 -> 10 | F10: =E10+F9 -> 12 | G10: =F10+G9 -> 13 | H10: =G10+H9 -> 14 | I10: =H10+I9 -> 16 | J10: =I10+J9 -> 17 | K10: =J10+K9 -> 20 | ... O10: =N10+O9 -> 30 | P10: =P9-O10 -> 0
A11: Spark Cumulative keys | B11: =B8 -> 528 | C11: =B11+C8 -> 528 | D11: =C11+D8 -> 756 | E11: =D11+E8 -> 846 | F11: =E11+F8 -> 1021 | G11: =F11+G8 -> 1076 | H11: =G11+H8 -> 1166 | I11: =H11+I8 -> 1285 | J11: =I11+J8 -> 1325 | ... O11: =N11+O8 -> 2257 | P11: =P8-O11 -> 0
A12: OPEN
A13: Total Keys | B13: 116 | C13: 104 | D13: 90 | E13: 40 | F13: 28 | G13: 0 | H13: 68 | I13: 43 | J13: 61 | K13: 14 | L13: 135 | M13: 152 | N13: 196 | O13: 268 | P13: =SUM(B13:O13) -> 1315
A14: Total Properties | B14: 4 | C14: 3 | D14: 2 | E14: 1 | F14: 1 | G14: 0 | H14: 2 | I14: 2 | J14: 3 | K14: 1 | L14: 4 | M14: 8 | N14: 9 | O14: =H28+H29+H30 -> 9 | P14: =SUM(B14:O14) -> 49
A15: Open Cumulative properties | B15: =B14 -> 4 | C15: =C14+B14 -> 7 | D15: =C15+D14 -> 9 | E15: =D15+E14 -> 10 | F15: =E15+F14 -> 11 | G15: =F15+G14 -> 11 | H15: =G15+H14 -> 13 | I15: =H15+I14 -> 15 | J15: =I15+J14 -> 18 | K15: =J15+K14 -> 19 | ... O15: =N15+O14 -> 49 | P15: =P14-O15 -> 0
A16: Open Cumulative keys | B16: =B13 -> 116 | C16: =B16+C13 -> 220 | D16: =C16+D13 -> 310 | E16: =D16+E13 -> 350 | F16: =E16+F13 -> 378 | G16: =F16+G13 -> 378 | H16: =G16+H13 -> 446 | I16: =H16+I13 -> 489 | J16: =I16+J13 -> 550 | ... O16: =N16+O13 -> 1315 | P16: =P13-O16 -> 0
A17: Overall
A18: Total properties | B18: =B4+B9+B14 -> 64 | C18: =C4+C9+C14 -> 4 | D18: =D4+D9+D14 -> 7 | E18: =E4+E9+E14 -> 3 | F18: =F4+F9+F14 -> 6 | G18: =G4+G9+G14 -> 2 | H18: =H4+H9+H14 -> 4 | I18: =I4+I9+I14 -> 5 | ... P18: =P4+P9+P14 -> 155
A19: Total keys | B19: =B3+B8+B13 -> 3033 | C19: =C3+C8+C13 -> 147 | D19: =D3+D8+D13 -> 410 | E19: =E3+E8+E13 -> 157 | F19: =F3+F8+F13 -> 313 | G19: =G3+G8+G13 -> 97 | H19: =H3+H8+H13 -> 188 | I19: =I3+I8+I13 -> 207 | ... P19: =P3+P8+P13 -> 6807
A20: Overall Cumulative properties | B20: =B18 -> 64 | C20: =C18+B20 -> 68 | D20: =D18+C20 -> 75 | E20: =E18+D20 -> 78 | F20: =F18+E20 -> 84 | G20: =G18+F20 -> 86 | H20: =H18+G20 -> 90 | I20: =I18+H20 -> 95 | J20: =J18+I20 -> 101 | ... O20: =O18+N20 -> 155 | P20: =P18-O20 -> 0
A21: Overall Cumulative keys | B21: =B19 -> 3033 | C21: =C19+B21 -> 3180 | D21: =D19+C21 -> 3590 | E21: =E19+D21 -> 3747 | F21: =F19+E21 -> 4060 | G21: =G19+F21 -> 4157 | H21: =H19+G21 -> 4345 | I21: =I19+H21 -> 4552 | J21: =J19+I21 -> 4743 | ... O21: =O19+N21 -> 6807 | P21: =P19-O21 -> 0
C25: April '26
B26: March '26 | C26: Week 1 | D26: Week 2 | E26: Week 3 | F26: Week 4 | G26: Week 5 | H26: Total
A27: Brands
A28: Open | B28: 9 | C28: 0 | D28: 3 | E28: 1 | F28: 0 | G28: 3 | H28: =SUM(C28:G28) -> 7
A29: Olive | B29: 3 | C29: 0 | D29: 0 | E29: 0 | F29: 0 | G29: 0 | H29: =SUM(C29:G29) -> 0
A30: Spark | B30: 4 | C30: 0 | D30: 0 | E30: 0 | F30: 1 | G30: 1 | H30: =SUM(C30:G30) -> 2
A33: Portfolio Update:
A34: 1. Open Brand:
A35: Global Stays (Blr) : 25 keys
A36: Xotel (HSR Layout): 25 keys
A37: SS Heritage (BLR) : 25 keys
A38: Diamond Park (Vizag): 20 keys
A39: MRV Inn (Chennai) : 19 keys
A40: Xotel, (Chennai Airport) : 16 keys
A41: Ambica Grand (Vizag) : 26 keys
A43: 2. Spark
A44: Le Grande (Andheri) : 58 keys
A45: Navsari : 54 keys
A47: 3. Sadahalli, Bangalore: The property has been formally converted from the Olive brand to Spark.

Sheet Operational
I1: Operational
C3: brought forwrad | D3: 45748 | E3: =EOMONTH(D3,1) -> 45808 | F3: =EOMONTH(E3,1) -> 45838 | G3: =EOMONTH(F3,1) -> 45869 | H3: =EOMONTH(G3,1) -> 45900 | I3: =EOMONTH(H3,1) -> 45930 | J3: =EOMONTH(I3,1) -> 45961 | K3: =EOMONTH(J3,1) -> 45991 | L3: =EOMONTH(K3,1) -> 46022 | ... P3: =EOMONTH(O3,1) -> 46142 | Q3: Total
B4: OLIVE
B5: Total Keys | C5: 1232 | D5: 0 | E5: 0 | F5: 90 | G5: 0 | H5: 0 | I5: 86 | J5: 0 | K5: 73 | L5: 40 | M5: 123 | O5: 56 | P5: 0 | Q5: =SUM(C5:P5) -> 1700
B6: Total Properties | C6: 32 | D6: 0 | E6: 0 | F6: 2 | G6: 0 | H6: 0 | I6: 1 | J6: 0 | K6: 1 | L6: 1 | M6: 3 | O6: 1 | P6: 0 | Q6: =SUM(C6:O6) -> 41
B7: Olive Cumulative keys | C7: =C5 -> 1232 | D7: =C7+D5 -> 1232 | E7: =D7+E5 -> 1232 | F7: =E7+F5 -> 1322 | G7: =F7+G5 -> 1322 | H7: =G7+H5 -> 1322 | I7: =H7+I5 -> 1408 | J7: =I7+J5 -> 1408 | K7: =J7+K5 -> 1481 | ... P7: =O7+P5 -> 1700 | Q7: =Q5-O7 -> 0
B8: Olive Cumulative Properties | C8: =C6 -> 32 | D8: =D6+C8 -> 32 | E8: =E6+D8 -> 32 | F8: =F6+E8 -> 34 | G8: =G6+F8 -> 34 | H8: =H6+G8 -> 34 | I8: =I6+H8 -> 35 | J8: =J6+I8 -> 35 | K8: =K6+J8 -> 36 | ... P8: =P6+O8 -> 41 | Q8: =Q6-O8 -> 0
B9: Open
B10: Total Keys | C10: 32 | D10: 0 | E10: 73 | F10: 26 | G10: 112 | H10: 30 | I10: 28 | J10: 51 | K10: 78 | L10: 20 | M10: 60 | N10: 0 | O10: 143 | P10: =I24 -> 99 | Q10: =SUM(C10:P10) -> 752 | R10: =Q5+Q10 -> 2452
B11: Total Properties | C11: 1 | D11: 0 | E11: 2 | F11: 1 | G11: 2 | H11: 1 | I11: 1 | J11: 2 | K11: 3 | L11: 1 | M11: 2 | N11: 0 | O11: 5 | P11: =I23 -> 3 | Q11: =SUM(C11:P11) -> 24
B12: Open Cumulative Keys | C12: =C10 -> 32 | D12: =C12+D10 -> 32 | E12: =D12+E10 -> 105 | F12: =E12+F10 -> 131 | G12: =F12+G10 -> 243 | H12: =G12+H10 -> 273 | I12: =H12+I10 -> 301 | J12: =I12+J10 -> 352 | K12: =J12+K10 -> 430 | ... P12: =O12+P10 -> 752 | Q12: =Q10-P12 -> 0
B13: Open Cumulative Properties | C13: =C11 -> 1 | D13: =D11+C13 -> 1 | E13: =E11+D13 -> 3 | F13: =F11+E13 -> 4 | G13: =G11+F13 -> 6 | H13: =H11+G13 -> 7 | I13: =I11+H13 -> 8 | J13: =J11+I13 -> 10 | K13: =K11+J13 -> 13 | ... O13: =O11+N13 -> 21 | P13: =O13+P11 -> 24 | Q13: =Q11-P13 -> 0
B14: Overall
B15: Total Keys | C15: =C5+C10 -> 1264 | D15: =D5+D10 -> 0 | E15: =E5+E10 -> 73 | F15: =F5+F10 -> 116 | G15: =G5+G10 -> 112 | H15: =H5+H10 -> 30 | I15: =I5+I10 -> 114 | J15: =J5+J10 -> 51 | ... P15: =P5+P10 -> 99 | Q15: =SUM(C15:P15) -> 2452
B16: Total Properties | C16: =C8+C13 -> 33 | D16: =D6+D11 -> 0 | E16: =E6+E11 -> 2 | F16: =F6+F11 -> 3 | G16: =G6+G11 -> 2 | H16: =H6+H11 -> 1 | I16: =I6+I11 -> 2 | J16: =J6+J11 -> 2 | K16: =K6+K11 -> 4 | ... P16: =P6+P11 -> 3 | Q16: =SUM(C16:P16) -> 65 | R16: =SUM(D16:O16) -> 29
B17: Overall Cumulative Keys | C17: =C15 -> 1264 | D17: =C17+D15 -> 1264 | E17: =D17+E15 -> 1337 | F17: =E17+F15 -> 1453 | G17: =F17+G15 -> 1565 | H17: =G17+H15 -> 1595 | I17: =H17+I15 -> 1709 | J17: =I17+J15 -> 1760 | K17: =J17+K15 -> 1911 | ... P17: =O17+P15 -> 2452 | Q17: =Q15-P17 -> 0
B18: Overall Cumulative Properties | C18: =C16 -> 33 | D18: =C18+D16 -> 33 | E18: =D18+E16 -> 35 | F18: =E18+F16 -> 38 | G18: =F18+G16 -> 40 | H18: =G18+H16 -> 41 | I18: =H18+I16 -> 43 | J18: =I18+J16 -> 45 | K18: =J18+K16 -> 49 | ... P18: =O18+P16 -> 65 | Q18: =Q16-P18 -> 0
D19: April '26
C20: March'26 | D20: Week 1 | E20: Week 2 | F20: Week 3 | G20: Week 4 | H20: Week 5 | I20: Total
B21: Brands
B22: Open
B23: -Properties | C23: 5 | D23: 0 | E23: 0 | F23: 2 | G23: 1 | H23: 0 | I23: =SUM(E23:H23) -> 3
B24: -Keys | C24: 143 | D24: 0 | E24: 0 | F24: =50+25 -> 75 | G24: 24 | H24: 0 | I24: =SUM(E24:H24) -> 99
B25: Olive | H25: =SUM(D25:G25) -> 0 | I25: =SUM(E25:H25) -> 0
B26: -Properties | C26: 1 | D26: 0 | E26: 0 | F26: 0 | G26: 0 | H26: =SUM(D26:G26) -> 0 | I26: =SUM(E26:H26) -> 0
B27: -Keys | C27: 55 | D27: 0 | E27: 0 | F27: 0 | G27: 0 | H27: =SUM(D27:G27) -> 0 | I27: =SUM(E27:H27) -> 0
B29: Total
B30: -Properties | C30: =C23+C26 -> 6 | D30: =SUM(D23+D26) -> 0 | E30: =SUM(E23+E26) -> 0 | F30: =SUM(F23+F26) -> 2 | G30: =SUM(G23+G26) -> 1 | H30: 0 | I30: =SUM(E30:H30) -> 3
B31: -Keys | C31: =C24+C27 -> 198 | D31: =D27+D24 -> 0 | E31: =E27+E24 -> 0 | F31: =F27+F24 -> 75 | G31: =G27+G24 -> 24 | H31: 0 | I31: =SUM(E31:H31) -> 99
B34: Portfolio Update: | H34: April '26 WIP | I34: Handover date | J34: Go-live date
B35: Operational Properties – Open Brand: | H35: Hulimavu, Bangalore | I35: Saturday, May 30th 2026 | J35: 15th June 2026
B36: 1. Chamier's Park : 25 keys | H36: Calangute, Goa | I36: Monday, June 15th 2026 | J36: 30th June 2026
B37: 2. The Botanica : 50 keys | H37: Nagarjuna/Marathahalli, Bangalore | I37: Friday, June 5th 2026 | J37: 20th June 2026
B38: 3. Sea Heights : 24 keys | H38: Nagavara, Bangalore | I38: Thursday, April 30th 2026 | J38: 15th May 2026
H39: JP Nagar, Bangalore | I39: Monday, May 11th 2026 | J39: 26th May 2026
H40: Olive Yelahanka near BMSIT BLR | I40: Monday, May 11th 2026 | J40: 26th May 2026
H41: Olive Sector 57 GUR | I41: Thursday, June 18th 2026 | J41: 3rd July 2026
H42: Vizag, AP | I42: Friday, May 15th 2026 | J42: 30th May 2026

Sheet Revenue
C1: Budget vs Actuals - April'26 - Managed properties '26 - same period
C3: Target | F3: Actuals | I3: % of Achievement
I4: Overall | J4: =F8/C8 -> 1.1823751
B5: Online | C5: 43407465 | F5: =44636779.71+325041 -> 44961821 | I5: Online | J5: =F5/C5 -> 1.0358085
B6: Offline | C6: =22445000+1718661 -> 24163661 | F6: 34932599 | I6: Offline | J6: =F6/C6 -> 1.4456666
B8: Total | C8: =SUM(C5:C7) -> 67571126 | F8: =SUM(F5:F7) -> 79894419
C10: YoY Growth - Managed properties
C12: April 25 | D12: Growth rates | F12: April 26
B14: Short stay | C14: 47580254 | D14: =(F14-C14)/C14 -> 0.67915077 | F14: =F8 -> 79894419
B15: Long stay | C15: 4406454 | D15: =(F15-C15)/C15 -> 0.13085284 | F15: 4983051
B17: Total | C17: =SUM(C14:C16) -> 51986708 | D17: =(F17-C17)/C17 -> 0.63267639 | F17: =SUM(F14:F16) -> 84877470
C19: MoM Growth - Franchised properties
C21: Feb | E21: March | G21: April
B23: Open | C23: 123995.05 | D23: =(E23-C23)/C23 -> 0.85151472 | E23: 229578.66 | F23: =(G23-E23)/E23 -> 0.13826533 | G23: 261321.43
B26: % of contribution | C26: 0.028 | E26: 0.042 | G26: 0.04

Sheet cashflow
B3: Cashflow - Summary
C4: April '26
C6: Target | D6: Received | J6: To be collected
B7: Inflow | D7: W1 | E7: W2 | F7: W3 | G7: W4 | H7: W5 | I7: Total
B8: TA fees | C8: =Inflow!C32 -> 18329400 | D8: =Inflow!E32 -> 0 | E8: =Inflow!F32 -> 70000 | F8: =Inflow!G32 -> 40000 | G8: =Inflow!H32 -> 40000 | H8: =Inflow!I32 -> 9024000 | I8: =SUM(D8:H8) -> 9174000 | J8: =C8-I8 -> 9155400
B9: Management fees | C9: =Inflow!C34 -> 11000000 | D9: =Inflow!E34 -> 355520 | E9: =Inflow!F34 -> 607764 | F9: =Inflow!G34 -> 2608847 | G9: =Inflow!H34 -> 4051004 | H9: =Inflow!I34 -> 1730425 | I9: =SUM(D9:H9) -> 9353560 | J9: =C9-I9 -> 1646440
B10: Profit Incentive | C10: =Inflow!C36 -> 500000 | D10: =Inflow!E36 -> 0 | E10: =Inflow!F36 -> 34880 | F10: =Inflow!G36 -> 0 | G10: =Inflow!H36 -> 0 | I10: =SUM(D10:G10) -> 34880 | J10: =C10-I10 -> 465120
B11: Total | C11: =SUM(C8:C10) -> 29829400 | D11: =SUM(D8:D10) -> 355520 | E11: =SUM(E8:E10) -> 712644 | F11: =SUM(F8:F10) -> 2648847 | G11: =SUM(G8:G10) -> 4091004 | H11: =SUM(H8:H10) -> 10754425 | I11: =SUM(I8:I10) -> 18562440 | J11: =SUM(J8:J10) -> 11266960
B12: Outflow - expected (Salaries + Reimbursements + Application fees + Sundries) | J12: =11350000+700000+1500000+3000000 -> 16550000
B15: Current bank balance | J15: =SUM(C16:C18) -> 14828607
B16: -Coliving Operations | C16: 10986723
B17: - Coliving | C17: 1812040
B18: -VARS | C18: 2029844
B20: Excess/Deficit (Expected outflow - current balance) | J20: =J15-J12 -> -1721393

Sheet Inflow
B4: Cashflow - Breakdown
C5: April
E6: Collections
B7: Inflow | C7: Target | E7: Received | K7: To be collected
B8: 1. TA fees | E8: W1 | F8: W2 | G8: W3 | H8: W4 | I8: W5 | J8: Total
B9: a) Spark
B10: Spark Ruby, Kolkata | C10: 1800000 | J10: =SUM(E10:I10) -> 0 | K10: =C10-J10 -> 1800000
B11: Bengaluru - Spark - Sheshadripuram | C11: 1000000 | J11: =SUM(E11:I11) -> 0 | K11: =C11-J11 -> 1000000
B12: Spark Junagad | C12: 825000 | J12: =SUM(E12:I12) -> 0 | K12: =C12-J12 -> 825000
B13: Spark Saddahalli ft Nandan | C13: 680400 | J13: =SUM(E13:I13) -> 0 | K13: =C13-J13 -> 680400
B14: Tirumala Bypass Road, Tirupati | C14: 1080000 | I14: 1080000 | J14: =SUM(E14:I14) -> 1080000 | K14: =C14-J14 -> 0
B15: Andheri - Le Grande | C15: 700000 | J15: =SUM(E15:I15) -> 0 | K15: =C15-J15 -> 700000
B16: Spark Rajkot | C16: 800000 | J16: =SUM(E16:I16) -> 0 | K16: =C16-J16 -> 800000
B17: Spark Navsari | C17: 2200000 | I17: 2200000 | J17: =SUM(E17:I17) -> 2200000 | K17: =C17-J17 -> 0
B18: Chakan | C18: 750000 | J18: =SUM(E18:I18) -> 0 | K18: =C18-J18 -> 750000
B19: REIT | C19: 5400000 | I19: 5400000 | J19: =SUM(E19:I19) -> 5400000 | K19: =C19-J19 -> 0
B20: Spark Vision Ventures - Tathawade | C20: 1750000 | J20: =SUM(E20:I20) -> 0 | K20: =C20-J20 -> 1750000
J21: =SUM(E21:I21) -> 0 | K21: =C21-J21 -> 0
B22: b) Olive | C22: =M22+O22 -> 0 | J22: =SUM(E22:I22) -> 0 | K22: =C22-J22 -> 0
B23: Olive Jayadeva Hospital | C23: 300000 | J23: =SUM(E23:I23) -> 0 | K23: =C23-J23 -> 300000
B24: Banjaara Hills | C24: 150000 | J24: =SUM(E24:I24) -> 0 | K24: =C24-J24 -> 150000
B25: Olive Bharatpur | C25: 400000 | J25: =SUM(E25:I25) -> 0 | K25: =C25-J25 -> 400000
B26: Olive Kakkanad Info Park | C26: 50000 | F26: 50000 | J26: =SUM(E26:I26) -> 50000 | K26: =C26-J26 -> 0
B27: Olive Dehradun | C27: 324000 | I27: 324000 | J27: =SUM(E27:I27) -> 324000 | K27: =C27-J27 -> 0
J28: =SUM(E28:I28) -> 0 | K28: =C28-J28 -> 0
J29: =SUM(E29:I29) -> 0 | K29: =C29-J29 -> 0
B30: c) Open set-up fees | C30: 120000 | E30: 0 | F30: 20000 | G30: 40000 | H30: 40000 | I30: 20000 | J30: =SUM(E30:I30) -> 120000 | K30: =C30-J30 -> 0
J31: =SUM(E31:I31) -> 0 | K31: =C31-J31 -> 0
B32: Total TA fees | C32: =SUM(C10:C30) -> 18329400 | D32: =SUM(D12:D30) -> 0 | E32: =SUM(E12:E30) -> 0 | F32: =SUM(F9:F30) -> 70000 | G32: =SUM(G9:G30) -> 40000 | H32: =SUM(H9:H30) -> 40000 | I32: =SUM(I9:I30) -> 9024000 | J32: =SUM(E32:I32) -> 9174000 | K32: =C32-J32 -> 9155400
K33: =C33-J33 -> 0
B34: 2. Management fees | C34: =11000000 -> 11000000 | E34: 355520 | F34: 607764 | G34: =3444773+127358-F34-E34 -> 2608847 | H34: =7658015-34880-SUM(E34:G34) -> 4051004 | I34: =J34-SUM(E34:H34) -> 1730425 | J34: =9082469+271091 -> 9353560 | K34: =C34-J34 -> 1646440
K35: =C35-J35 -> 0
B36: 3. Profit Incentive | C36: 500000 | E36: 0 | F36: 34880 | J36: =SUM(E36:I36) -> 34880 | K36: =C36-J36 -> 465120
K37: =C37-J37 -> 0
B38: Total Inflow | C38: =C32+C34+C36 -> 29829400 | D38: =D32+D34+D36 -> 0 | E38: =E32+E34+E36 -> 355520 | F38: =F32+F34+F36 -> 712644 | G38: =G32+G34+G36 -> 2648847 | H38: =H32+H34+H36 -> 4091004 | I38: =I32+I34+I36 -> 10754425 | J38: =J32+J34+J36 -> 18562440 | K38: =C38-J38 -> 11266960

Sheet Sheet1
C5: Dairy circle | D5: 400000 | F5: -Salaries | I5: 10600000 | K5: -Salaries | N5: 11000000
C6: hitech | D6: 200000 | F6: -Car EMI | I6: 124266 | K6: -Car EMI | N6: 124266
C7: kundahalli | D7: 300000 | F7: -EE reimbursements | I7: 500000 | K7: -EE reimbursements | N7: 500000
C8: vijawada | D8: =350000*0 -> 0 | F8: -medical insurance | I8: 500000 | K8: -medical insurance | N8: 500000
C9: Vasanth nagar | D9: 350000 | F9: -OPC | I9: 2000000 | K9: -Hisca | N9: 500000
C10: Rajaji nahar | F10: -Rent | I10: 916634.45 | K10: -Zoho | N10: 361000
C11: Domlur | K11: Travel agency | N11: 500000
C12: Meera - Goa | D12: 100000 | K12: -Kingshuk | N12: 200000
C13: Indiranagar | D13: 200000 | I13: =SUM(I5:I12) -> 14640900 | N13: =SUM(N5:N12) -> 13685266
C14: Nivasa | D14: 100000
D16: =SUM(D5:D15) -> 1650000
