Workbook

Sheet Signings
B1: brought forward | C1: 45748 | D1: =EOMONTH(C1,1) -> 45808 | E1: =EOMONTH(D1,1) -> 45838 | F1: =EOMONTH(E1,1) -> 45869 | G1: =EOMONTH(F1,1) -> 45900 | H1: =EOMONTH(G1,1) -> 45930 | I1: =EOMONTH(H1,1) -> 45961 | J1: =EOMONTH(I1,1) -> 45991 | K1: =EOMONTH(J1,1) -> 46022 | ... O1: =EOMONTH(N1,1) -> 46142 | P1: Total
A2: OLIVE
A3: Total Keys | B3: 2389 | C3: 43 | D3: 92 | E3: 27 | F3: 110 | G3: 42 | H3: 30 | I3: 45 | J3: 90 | K3: 60 | L3: 61 | M3: 135 | N3: 111 | O3: 0 | P3: =SUM(B3:O3) -> 3235
A4: Total Properties | B4: 54 | C4: 1 | D4: 2 | E4: 1 | F4: 3 | G4: 1 | H4: 1 | I4: 1 | J4: 2 | K4: 2 | L4: 1 | M4: 4 | N4: 3 | O4: =G25 -> 0 | P4: =SUM(B4:O4) -> 76
A5: Cumulative Properties | B5: =B4 -> 54 | C5: =C4+B4 -> 55 | D5: =C5+D4 -> 57 | E5: =D5+E4 -> 58 | F5: =E5+F4 -> 61 | G5: =F5+G4 -> 62 | H5: =G5+H4 -> 63 | I5: =H5+I4 -> 64 | J5: =I5+J4 -> 66 | K5: =J5+K4 -> 68 | ... O5: =N5+O4 -> 76 | P5: =P4-O5 -> 0
A6: Cumulative keys | B6: =B3 -> 2389 | C6: =B6+C3 -> 2432 | D6: =C6+D3 -> 2524 | E6: =D6+E3 -> 2551 | F6: =E6+F3 -> 2661 | G6: =F6+G3 -> 2703 | H6: =G6+H3 -> 2733 | I6: =H6+I3 -> 2778 | J6: =I6+J3 -> 2868 | ... O6: =N6+O3 -> 3235 | P6: =P3-O6 -> 0
A7: SPARK
A8: Total Keys | B8: 528 | D8: 228 | E8: 90 | F8: 175 | G8: 55 | H8: 90 | I8: 119 | J8: 40 | K8: 338 | L8: 316 | M8: 51 | N8: 227 | O8: 0 | P8: =SUM(B8:O8) -> 2257
A9: Total Properties | B9: 6 | C9: 0 | D9: 3 | E9: 1 | F9: 2 | G9: 1 | H9: 1 | I9: 2 | J9: 1 | K9: 3 | L9: 3 | M9: 1 | N9: 4 | O9: =G26 -> 0 | P9: =SUM(B9:O9) -> 28
A10: Cumulative | B10: =B9 -> 6 | C10: =C9+B9 -> 6 | D10: =C10+D9 -> 9 | E10: =D10+E9 -> 10 | F10: =E10+F9 -> 12 | G10: =F10+G9 -> 13 | H10: =G10+H9 -> 14 | I10: =H10+I9 -> 16 | J10: =I10+J9 -> 17 | K10: =J10+K9 -> 20 | ... O10: =N10+O9 -> 28 | P10: =P9-O10 -> 0
A11: Cumulative keys | B11: =B8 -> 528 | C11: =B11+C8 -> 528 | D11: =C11+D8 -> 756 | E11: =D11+E8 -> 846 | F11: =E11+F8 -> 1021 | G11: =F11+G8 -> 1076 | H11: =G11+H8 -> 1166 | I11: =H11+I8 -> 1285 | J11: =I11+J8 -> 1325 | ... O11: =N11+O8 -> 2257 | P11: =P8-O11 -> 0
A12: OPEN
A13: Total Keys | B13: 116 | C13: 104 | D13: 90 | E13: 40 | F13: 28 | G13: 0 | H13: 68 | I13: 43 | J13: 61 | K13: 14 | L13: 135 | M13: 152 | N13: 196 | O13: =25+25+25 -> 75 | P13: =SUM(B13:O13) -> 1122
A14: Total Properties | B14: 4 | C14: 3 | D14: 2 | E14: 1 | F14: 1 | G14: 0 | H14: 2 | I14: 2 | J14: 3 | K14: 1 | L14: 4 | M14: 8 | N14: 9 | O14: =G24 -> 3 | P14: =SUM(B14:O14) -> 43
A15: Cumulative | B15: =B14 -> 4 | C15: =C14+B14 -> 7 | D15: =C15+D14 -> 9 | E15: =D15+E14 -> 10 | F15: =E15+F14 -> 11 | G15: =F15+G14 -> 11 | H15: =G15+H14 -> 13 | I15: =H15+I14 -> 15 | J15: =I15+J14 -> 18 | K15: =J15+K14 -> 19 | ... O15: =N15+O14 -> 43 | P15: =P14-O15 -> 0
A16: Cumulative keys | B16: =B13 -> 116 | C16: =B16+C13 -> 220 | D16: =C16+D13 -> 310 | E16: =D16+E13 -> 350 | F16: =E16+F13 -> 378 | G16: =F16+G13 -> 378 | H16: =G16+H13 -> 446 | I16: =H16+I13 -> 489 | J16: =I16+J13 -> 550 | ... O16: =N16+O13 -> 1122 | P16: =P13-O16 -> 0
A17: Total properties | P17: =P4+P9+P14 -> 147
A18: Total keys | P18: =P3+P8+P13 -> 6614
C21: April '26
B22: March '26 | C22: Week 1 | D22: Week 2 | E22: Week 3 | F22: Week 4 | G22: Total
A23: Brands
A24: Open | B24: 9 | C24: 0 | D24: 3 | E24: 0 | F24: 0 | G24: =SUM(C24:F24) -> 3
A25: Olive | B25: 3 | C25: 0 | D25: 0 | E25: 0 | F25: 0 | G25: =SUM(C25:F25) -> 0
A26: Spark | B26: 4 | C26: 0 | D26: 0 | E26: 0 | F26: 0 | G26: =SUM(C26:F26) -> 0
A29: Portfolio Update:
A30: Open: Global stays - Bangalore (25) 2. Xotel - Chennai (22)

Sheet Operational
I1: Operational
C3: brought forwrad | D3: 45748 | E3: =EOMONTH(D3,1) -> 45808 | F3: =EOMONTH(E3,1) -> 45838 | G3: =EOMONTH(F3,1) -> 45869 | H3: =EOMONTH(G3,1) -> 45900 | I3: =EOMONTH(H3,1) -> 45930 | J3: =EOMONTH(I3,1) -> 45961 | K3: =EOMONTH(J3,1) -> 45991 | L3: =EOMONTH(K3,1) -> 46022 | ... O3: =EOMONTH(N3,1) -> 46112 | P3: Total
B4: OLIVE
B5: Total Keys | C5: 1232 | D5: 0 | E5: 0 | F5: 90 | G5: 0 | H5: 0 | I5: 86 | J5: 0 | K5: 73 | L5: 40 | M5: 123 | O5: 56 | P5: =SUM(C5:O5) -> 1700
B6: Total Properties | C6: 32 | D6: 0 | E6: 0 | F6: 2 | G6: 0 | H6: 0 | I6: 1 | J6: 0 | K6: 1 | L6: 1 | M6: 3 | O6: 1 | P6: =SUM(C6:O6) -> 41
B7: Cumulative keys | C7: =C5 -> 1232 | D7: =C7+D5 -> 1232 | E7: =D7+E5 -> 1232 | F7: =E7+F5 -> 1322 | G7: =F7+G5 -> 1322 | H7: =G7+H5 -> 1322 | I7: =H7+I5 -> 1408 | J7: =I7+J5 -> 1408 | K7: =J7+K5 -> 1481 | ... O7: =N7+O5 -> 1700 | P7: =P5-O7 -> 0
B8: Cumulative Properties | C8: =C6 -> 32 | D8: =D6+C8 -> 32 | E8: =E6+D8 -> 32 | F8: =F6+E8 -> 34 | G8: =G6+F8 -> 34 | H8: =H6+G8 -> 34 | I8: =I6+H8 -> 35 | J8: =J6+I8 -> 35 | K8: =K6+J8 -> 36 | ... O8: =O6+N8 -> 41 | P8: =P6-O8 -> 0
B9: Open
B10: Total Keys | C10: 32 | D10: 0 | E10: 73 | F10: 26 | G10: 112 | H10: 30 | I10: 28 | J10: 51 | K10: 78 | L10: 20 | M10: 60 | N10: 0 | O10: 143 | P10: =SUM(C10:O10) -> 653
B11: Total Properties | C11: 1 | D11: 0 | E11: 2 | F11: 1 | G11: 2 | H11: 1 | I11: 1 | J11: 2 | K11: 3 | L11: 1 | M11: 2 | N11: 0 | O11: 5 | P11: =SUM(C11:O11) -> 21
B12: Cumulative Keys | C12: =C10 -> 32 | D12: =C12+D10 -> 32 | E12: =D12+E10 -> 105 | F12: =E12+F10 -> 131 | G12: =F12+G10 -> 243 | H12: =G12+H10 -> 273 | I12: =H12+I10 -> 301 | J12: =I12+J10 -> 352 | K12: =J12+K10 -> 430 | ... O12: =N12+O10 -> 653 | P12: =P10-O12 -> 0
B13: Cumulative Properties | C13: =C11 -> 1 | D13: =D11+C13 -> 1 | E13: =E11+D13 -> 3 | F13: =F11+E13 -> 4 | G13: =G11+F13 -> 6 | H13: =H11+G13 -> 7 | I13: =I11+H13 -> 8 | J13: =J11+I13 -> 10 | K13: =K11+J13 -> 13 | ... O13: =O11+N13 -> 21 | P13: =P11-O13 -> 0
D14: April '26
C15: March'26 | D15: Week 1 | E15: Week 2 | F15: Week 3 | G15: Week 4 | H15: Total
B16: Brands
B17: Open
B18: -Properties | C18: 5 | D18: 0 | E18: 0 | F18: 0 | G18: 0 | H18: =SUM(D18:G18) -> 0
B19: -Keys | C19: 143 | D19: 0 | E19: 0 | F19: 0 | G19: 0 | H19: =SUM(D19:G19) -> 0
B20: Olive | H20: =SUM(D20:G20) -> 0
B21: -Properties | C21: 0 | D21: 0 | E21: 0 | F21: 0 | G21: 0 | H21: =SUM(D21:G21) -> 0
B22: -Keys | C22: 55 | D22: 0 | E22: 0 | F22: 0 | G22: 0 | H22: =SUM(D22:G22) -> 0
B24: Total
B25: -Properties | C25: =C18+C21 -> 5 | D25: =SUM(D18+D21) -> 0 | E25: =SUM(E18+E21) -> 0 | F25: =SUM(F18+F21) -> 0 | G25: =SUM(G18+G21) -> 0 | H25: =SUM(D25:G25) -> 0
B26: -Keys | C26: =C19+C22 -> 198 | D26: =D22+D19 -> 0 | E26: =E22+E19 -> 0 | F26: =F22+F19 -> 0 | G26: =G22+G19 -> 0 | H26: =SUM(D26:G26) -> 0
D29: March '26 WIP | H29: Keys | I29: Target date
D30: Olive
D31: Nagavara (JC Reddy) | H31: 105 | I31: April '26
D32: Journalist colony (Hyd) | H32: 35 | I32: April '26
D33: VIP Road, Vizag (Venkata Savitri Ravisetty) | H33: 30 | I33: April '26
D34: JP Nagar (Santosh) | H34: 39 | I34: April '26
D35: Hulimavu | H35: 56 | I35: April '26
D36: Guntur | H36: 36 | I36: April '26

Sheet Revenue
C1: April'26 - same period 26 same period '26 - same period
C3: Target | F3: Actuals | I3: Achievement
I4: Overall | J4: =F8/C8 -> 0.39644458
B5: Online | C5: 18176683 | D5: =C5/$C$8 -> 0.74706947 | F5: 5926682.1 | G5: =F5/F8 -> 0.61443439 | I5: Online | J5: =F5/C5 -> 0.32605961
B6: Offline | C6: 6153963.1 | D6: =C6/$C$8 -> 0.25293053 | F6: 3719070.5 | G6: =F6/F8 -> 0.38556561 | I6: Offline | J6: =F6/C6 -> 0.60433747
B8: Total | C8: =SUM(C5:C7) -> 24330646 | F8: =SUM(F5:F7) -> 9645752.6
C10: April'26 - same period
C12: April 25 | F12: April 26 | I12: YoY - growth
I13: Overall | J13: =F17/C17-1 -> 0.67530288
B14: Online | C14: 3495262.3 | D14: =C14/C17 -> 0.60706751 | F14: 5926682.1 | G14: =F14/F17 -> 0.61443439 | I14: Online | J14: =F14/C14-1 -> 0.69563299
B15: Offline | C15: 2262354.9 | D15: =C15/C17 -> 0.39293249 | F15: 3719070.5 | G15: =F15/F17 -> 0.38556561 | I15: Offline | J15: =F15/C15-1 -> 0.64389353
B17: Total | C17: =SUM(C14:C16) -> 5757617.2 | F17: =SUM(F14:F16) -> 9645752.6
C19: March'26 - same store - stable properties
C21: March 25 | F21: March 26 | I21: YoY - growth
I22: Overall | J22: =F26/C26-1 -> 0.14412757
B23: Revenue | C23: 45740209 | F23: 52332634
B26: Total | C26: =SUM(C23:C25) -> 45740209 | F26: =SUM(F23:F25) -> 52332634

Sheet cashflow
B3: Cashflow - Summary
C4: March '26
C6: Target | D6: Received | H6: Expected
B7: Inflow | D7: W1 | E7: W2 | F7: W3 | G7: W4
B8: TA fees | C8: =Inflow!C30 -> 12185400 | D8: =Inflow!E30 -> 0 | H8: =C8-D8 -> 12185400
B9: Management fees | C9: =Inflow!C33 -> 13000000 | D9: =Inflow!E33 -> 355520 | H9: =C9-D9 -> 12644480
B10: Profit Incentive | C10: =Inflow!C35 -> 500000 | D10: =Inflow!E35 -> 0 | H10: =C10-D10 -> 500000
B11: Total | C11: =SUM(C8:C10) -> 25685400 | D11: =SUM(D8:D10) -> 355520 | E11: =SUM(E8:E10) -> 0 | F11: =SUM(F8:F10) -> 0 | G11: =SUM(G8:G10) -> 0 | H11: =SUM(H8:H10) -> 25329880
B12: Outflow | H12: 19500000
B15: Current bank balance | H15: =SUM(C16:C18) -> 6263152
B16: -Coliving Operations | C16: 5317640
B17: - Coliving | C17: 56251
B18: -VARS | C18: 889261
B20: Closing Cash - expected | H20: =H11+H15-H12 -> 12093032

Sheet Inflow
B4: Cashflow - Breakdown
C5: April
E6: Collections
B7: Inflow | C7: Target | E7: Received | I7: Expected | J7: Total
B8: 1. TA fees | E8: W1 | F8: W2 | G8: W3 | H8: W4
B9: a) Spark
B10: Spark Ruby, Kolkata | C10: 1800000 | I10: =C10-E10 -> 1800000
B11: Spark Mussoriee | C11: 500000 | I11: =C11-E11 -> 500000
B12: Bengaluru - Spark - Sheshadripuram | C12: 1000000 | I12: =C12-E12 -> 1000000
B13: Chakan | C13: 750000 | I13: =C13-E13 -> 750000
B14: Spark Junagad | C14: 825000 | I14: =C14-E14 -> 825000
B15: Spark Saddahalli ft Nandan | C15: 680400 | I15: =C15-E15 -> 680400
B16: Tirumala Bypass Road, Tirupati | C16: 1080000 | I16: =C16-E16 -> 1080000
I17: =C17-E17 -> 0
B18: REIT | C18: 5000000 | I18: =C18-E18 -> 5000000
I19: =C19-E19 -> 0
B20: b) Olive | C20: =L20+N20 -> 0 | I20: =C20-E20 -> 0
B21: Olive Jayadeva Hospital | C21: 300000 | I21: =C21-E21 -> 300000
B22: Banjaara Hills | C22: 150000 | I22: =C22-E22 -> 150000
I23: =C23-E23 -> 0
I24: =C24-E24 -> 0
I25: =C25-E25 -> 0
I26: =C26-E26 -> 0
I27: =C27-E27 -> 0
B28: c) Open set-up fees | C28: 100000 | E28: 0 | I28: =C28-E28 -> 100000
I29: =C29-E29 -> 0
B30: Total TA fees | C30: =SUM(C10:C28) -> 12185400 | D30: =SUM(D10:D28) -> 0 | E30: =SUM(E10:E28) -> 0 | F30: =SUM(F10:F28) -> 0 | G30: =SUM(G10:G28) -> 0 | H30: =SUM(H10:H28) -> 0 | I30: =C30-E30 -> 12185400 | J30: =E30+I30 -> 12185400
B33: 2. Management fees | C33: =13000000 -> 13000000 | E33: 355520 | I33: =C33-E33 -> 12644480
I34: =C34-E34 -> 0
B35: 3. Profit Incentive | C35: 500000 | E35: 0 | I35: =C35-E35 -> 500000 | J35: =SUM(E35:F35) -> 0
B39: Total Inflow | E39: =E35+E33+E30 -> 355520 | I39: =I35+I33+I30 -> 25329880 | J39: =I39+E39 -> 25685400

Sheet Sheet1
C5: Dairy circle | D5: 400000 | F5: -Salaries | I5: 10600000 | K5: -Salaries | N5: 11000000
C6: hitech | D6: 200000 | F6: -Car EMI | I6: 124266 | K6: -Car EMI | N6: 124266
C7: kundahalli | D7: 300000 | F7: -EE reimbursements | I7: 500000 | K7: -EE reimbursements | N7: 500000
C8: vijawada | D8: =350000*0 -> 0 | F8: -medical insurance | I8: 500000 | K8: -medical insurance | N8: 500000
C9: Vasanth nagar | D9: 350000 | F9: -OPC | I9: 2000000 | K9: -Hisca | N9: 500000
C10: Rajaji nahar | F10: -Rent | I10: 916634.45 | K10: -Zoho | N10: 361000
C11: Domlur | K11: Travel agency | N11: 500000
C12: Meera - Goa | D12: 100000 | K12: -Kingshuk | N12: 200000
C13: Indiranagar | D13: 200000 | I13: =SUM(I5:I12) -> 14640900 | N13: =SUM(N5:N12) -> 13685266
C14: Nivasa | D14: 100000
D16: =SUM(D5:D15) -> 1650000
