Workbook

Sheet Signings
B1: brought forward | C1: 45748 | D1: =EOMONTH(C1,1) -> 45808 | E1: =EOMONTH(D1,1) -> 45838 | F1: =EOMONTH(E1,1) -> 45869 | G1: =EOMONTH(F1,1) -> 45900 | H1: =EOMONTH(G1,1) -> 45930 | I1: =EOMONTH(H1,1) -> 45961 | J1: =EOMONTH(I1,1) -> 45991 | K1: =EOMONTH(J1,1) -> 46022 | ... O1: =EOMONTH(N1,1) -> 46142 | P1: Total
A2: OLIVE
A3: Total Keys | B3: 2389 | C3: 43 | D3: 92 | E3: 27 | F3: 110 | G3: 42 | H3: 30 | I3: 45 | J3: 90 | K3: 60 | L3: 61 | M3: 135 | N3: 111 | O3: 0 | P3: =SUM(B3:O3) -> 3235
A4: Total Properties | B4: 54 | C4: 1 | D4: 2 | E4: 1 | F4: 3 | G4: 1 | H4: 1 | I4: 1 | J4: 2 | K4: 2 | L4: 1 | M4: 4 | N4: 3 | O4: =G25 -> 0 | P4: =SUM(B4:O4) -> 76
A5: Cumulative Properties | B5: =B4 -> 54 | C5: =C4+B4 -> 55 | D5: =C5+D4 -> 57 | E5: =D5+E4 -> 58 | F5: =E5+F4 -> 61 | G5: =F5+G4 -> 62 | H5: =G5+H4 -> 63 | I5: =H5+I4 -> 64 | J5: =I5+J4 -> 66 | K5: =J5+K4 -> 68 | ... O5: =N5+O4 -> 76 | P5: =P4-O5 -> 0
A6: Cumulative keys | B6: =B3 -> 2389 | C6: =B6+C3 -> 2432 | D6: =C6+D3 -> 2524 | E6: =D6+E3 -> 2551 | F6: =E6+F3 -> 2661 | G6: =F6+G3 -> 2703 | H6: =G6+H3 -> 2733 | I6: =H6+I3 -> 2778 | J6: =I6+J3 -> 2868 | ... O6: =N6+O3 -> 3235 | P6: =P3-O6 -> 0
A7: SPARK
A8: Total Keys | B8: 528 | D8: 228 | E8: 90 | F8: 175 | G8: 55 | H8: 90 | I8: 119 | J8: 40 | K8: 338 | L8: 316 | M8: 51 | N8: 227 | O8: 0 | P8: =SUM(B8:O8) -> 2257
A9: Total Properties | B9: 6 | C9: 0 | D9: 3 | E9: 1 | F9: 2 | G9: 1 | H9: 1 | I9: 2 | J9: 1 | K9: 3 | L9: 3 | M9: 1 | N9: 4 | O9: =G26 -> 1 | P9: =SUM(B9:O9) -> 29
A10: Cumulative | B10: =B9 -> 6 | C10: =C9+B9 -> 6 | D10: =C10+D9 -> 9 | E10: =D10+E9 -> 10 | F10: =E10+F9 -> 12 | G10: =F10+G9 -> 13 | H10: =G10+H9 -> 14 | I10: =H10+I9 -> 16 | J10: =I10+J9 -> 17 | K10: =J10+K9 -> 20 | ... O10: =N10+O9 -> 29 | P10: =P9-O10 -> 0
A11: Cumulative keys | B11: =B8 -> 528 | C11: =B11+C8 -> 528 | D11: =C11+D8 -> 756 | E11: =D11+E8 -> 846 | F11: =E11+F8 -> 1021 | G11: =F11+G8 -> 1076 | H11: =G11+H8 -> 1166 | I11: =H11+I8 -> 1285 | J11: =I11+J8 -> 1325 | ... O11: =N11+O8 -> 2257 | P11: =P8-O11 -> 0
A12: OPEN
A13: Total Keys | B13: 116 | C13: 104 | D13: 90 | E13: 40 | F13: 28 | G13: 0 | H13: 68 | I13: 43 | J13: 61 | K13: 14 | L13: 135 | M13: 152 | N13: 196 | O13: =25+25+25+20 -> 95 | P13: =SUM(B13:O13) -> 1142
A14: Total Properties | B14: 4 | C14: 3 | D14: 2 | E14: 1 | F14: 1 | G14: 0 | H14: 2 | I14: 2 | J14: 3 | K14: 1 | L14: 4 | M14: 8 | N14: 9 | O14: =G24 -> 4 | P14: =SUM(B14:O14) -> 44
A15: Cumulative | B15: =B14 -> 4 | C15: =C14+B14 -> 7 | D15: =C15+D14 -> 9 | E15: =D15+E14 -> 10 | F15: =E15+F14 -> 11 | G15: =F15+G14 -> 11 | H15: =G15+H14 -> 13 | I15: =H15+I14 -> 15 | J15: =I15+J14 -> 18 | K15: =J15+K14 -> 19 | ... O15: =N15+O14 -> 44 | P15: =P14-O15 -> 0
A16: Cumulative keys | B16: =B13 -> 116 | C16: =B16+C13 -> 220 | D16: =C16+D13 -> 310 | E16: =D16+E13 -> 350 | F16: =E16+F13 -> 378 | G16: =F16+G13 -> 378 | H16: =G16+H13 -> 446 | I16: =H16+I13 -> 489 | J16: =I16+J13 -> 550 | ... O16: =N16+O13 -> 1142 | P16: =P13-O16 -> 0
A17: Total properties | P17: =P4+P9+P14 -> 149
A18: Total keys | P18: =P3+P8+P13 -> 6634
C21: April '26
B22: March '26 | C22: Week 1 | D22: Week 2 | E22: Week 3 | F22: Week 4 | G22: Total
A23: Brands
A24: Open | B24: 9 | C24: 0 | D24: 3 | E24: 1 | F24: 0 | G24: =SUM(C24:F24) -> 4
A25: Olive | B25: 3 | C25: 0 | D25: 0 | E25: 0 | F25: 0 | G25: =SUM(C25:F25) -> 0
A26: Spark | B26: 4 | C26: 0 | D26: 0 | E26: 0 | F26: 1 | G26: =SUM(C26:F26) -> 1
A29: Portfolio Update:
A30: 1. New Signings – Open Brand:
A31: Global Stays: 25 keys
A32: Xotel HSR Layout: 25 keys
A33: SS Heritage: 25 keys
A34: Diamond Park (Vizag): 20 keys
A36: 2. Sadahalli, Bangalore: The property has been formally converted from the Olive brand to Spark.
A37: 3. MA executed with Le Grande for the Spark property in Mumbai.

Sheet Operational
I1: Operational
C3: brought forwrad | D3: 45748 | E3: =EOMONTH(D3,1) -> 45808 | F3: =EOMONTH(E3,1) -> 45838 | G3: =EOMONTH(F3,1) -> 45869 | H3: =EOMONTH(G3,1) -> 45900 | I3: =EOMONTH(H3,1) -> 45930 | J3: =EOMONTH(I3,1) -> 45961 | K3: =EOMONTH(J3,1) -> 45991 | L3: =EOMONTH(K3,1) -> 46022 | ... P3: =EOMONTH(O3,1) -> 46142 | Q3: Total
B4: OLIVE
B5: Total Keys | C5: 1232 | D5: 0 | E5: 0 | F5: 90 | G5: 0 | H5: 0 | I5: 86 | J5: 0 | K5: 73 | L5: 40 | M5: 123 | O5: 56 | P5: 0 | Q5: =SUM(C5:P5) -> 1700
B6: Total Properties | C6: 32 | D6: 0 | E6: 0 | F6: 2 | G6: 0 | H6: 0 | I6: 1 | J6: 0 | K6: 1 | L6: 1 | M6: 3 | O6: 1 | P6: 0 | Q6: =SUM(C6:O6) -> 41
B7: Cumulative keys | C7: =C5 -> 1232 | D7: =C7+D5 -> 1232 | E7: =D7+E5 -> 1232 | F7: =E7+F5 -> 1322 | G7: =F7+G5 -> 1322 | H7: =G7+H5 -> 1322 | I7: =H7+I5 -> 1408 | J7: =I7+J5 -> 1408 | K7: =J7+K5 -> 1481 | ... P7: =O7+P5 -> 1700 | Q7: =Q5-O7 -> 0
B8: Cumulative Properties | C8: =C6 -> 32 | D8: =D6+C8 -> 32 | E8: =E6+D8 -> 32 | F8: =F6+E8 -> 34 | G8: =G6+F8 -> 34 | H8: =H6+G8 -> 34 | I8: =I6+H8 -> 35 | J8: =J6+I8 -> 35 | K8: =K6+J8 -> 36 | ... P8: =P6+O8 -> 41 | Q8: =Q6-O8 -> 0
B9: Open
B10: Total Keys | C10: 32 | D10: 0 | E10: 73 | F10: 26 | G10: 112 | H10: 30 | I10: 28 | J10: 51 | K10: 78 | L10: 20 | M10: 60 | N10: 0 | O10: 143 | P10: =H22 -> 99 | Q10: =SUM(C10:P10) -> 752 | R10: =Q5+Q10 -> 2452
B11: Total Properties | C11: 1 | D11: 0 | E11: 2 | F11: 1 | G11: 2 | H11: 1 | I11: 1 | J11: 2 | K11: 3 | L11: 1 | M11: 2 | N11: 0 | O11: 5 | P11: =H21 -> 3 | Q11: =SUM(C11:P11) -> 24
B12: Cumulative Keys | C12: =C10 -> 32 | D12: =C12+D10 -> 32 | E12: =D12+E10 -> 105 | F12: =E12+F10 -> 131 | G12: =F12+G10 -> 243 | H12: =G12+H10 -> 273 | I12: =H12+I10 -> 301 | J12: =I12+J10 -> 352 | K12: =J12+K10 -> 430 | ... P12: =O12+P10 -> 752 | Q12: =Q10-P12 -> 0
B13: Cumulative Properties | C13: =C11 -> 1 | D13: =D11+C13 -> 1 | E13: =E11+D13 -> 3 | F13: =F11+E13 -> 4 | G13: =G11+F13 -> 6 | H13: =H11+G13 -> 7 | I13: =I11+H13 -> 8 | J13: =J11+I13 -> 10 | K13: =K11+J13 -> 13 | ... O13: =O11+N13 -> 21 | P13: =O13+P11 -> 24 | Q13: =Q11-P13 -> 0
R14: =SUM(D14:O14) -> 0
D17: April '26 | P17: =P8+P13 -> 65
C18: March'26 | D18: Week 1 | E18: Week 2 | F18: Week 3 | G18: Week 4 | H18: Total | P18: =P7+P12 -> 2452
B19: Brands
B20: Open
B21: -Properties | C21: 5 | D21: 0 | E21: 0 | F21: 2 | G21: 1 | H21: =SUM(D21:G21) -> 3
B22: -Keys | C22: 143 | D22: 0 | E22: 0 | F22: =50+25 -> 75 | G22: 24 | H22: =SUM(D22:G22) -> 99
B23: Olive | H23: =SUM(D23:G23) -> 0
B24: -Properties | C24: 0 | D24: 0 | E24: 0 | F24: 0 | G24: 0 | H24: =SUM(D24:G24) -> 0
B25: -Keys | C25: 55 | D25: 0 | E25: 0 | F25: 0 | G25: 0 | H25: =SUM(D25:G25) -> 0
B27: Total
B28: -Properties | C28: =C21+C24 -> 5 | D28: =SUM(D21+D24) -> 0 | E28: =SUM(E21+E24) -> 0 | F28: =SUM(F21+F24) -> 2 | G28: =SUM(G21+G24) -> 1 | H28: =SUM(D28:G28) -> 3
B29: -Keys | C29: =C22+C25 -> 198 | D29: =D25+D22 -> 0 | E29: =E25+E22 -> 0 | F29: =F25+F22 -> 75 | G29: =G25+G22 -> 24 | H29: =SUM(D29:G29) -> 99
B32: Portfolio Update: | H32: April '26 WIP | I32: Handover date | J32: Go-live date
B33: Operational Properties – Open Brand: | H33: Hulimavu, Bangalore | I33: Saturday, May 30th 2026 | J33: 15th June 2026
B34: 1. Chamier's Park : 25 keys | H34: Calangute, Goa | I34: Monday, June 15th 2026 | J34: 30th June 2026
B35: 2. The Botanica : 50 keys | H35: Nagarjuna/Marathahalli, Bangalore | I35: Friday, June 5th 2026 | J35: 20th June 2026
B36: 3. Sea Heights : 24 keys | H36: Nagavara, Bangalore | I36: Thursday, April 30th 2026 | J36: 15th May 2026
H37: JP Nagar, Bangalore | I37: Monday, May 11th 2026 | J37: 26th May 2027
H38: Olive Yelahanka near BMSIT BLR | I38: Monday, May 11th 2026 | J38: 26th May 2027
H39: Olive Sector 57 GUR | I39: Thursday, June 18th 2026 | J39: 3rd July 2026
H40: Vizag, AP | I40: Friday, May 15th 2026 | J40: 30th May 2026

Sheet Revenue
C1: April'26 - same period 26 same period '26 - same period
C3: Target | F3: Actuals | I3: Achievement
I4: Overall | J4: =F8/C8 -> 0.97543859
B5: Online | C5: 39646623 | D5: =C5/$C$8 -> 0.68827808 | F5: 34291603 | G5: =F5/F8 -> 0.61030312 | I5: Online | J5: =F5/C5 -> 0.86493124
B6: Offline | C6: 17956000 | D6: =C6/$C$8 -> 0.31172192 | F6: 21896219 | G6: =F6/F8 -> 0.38969688 | I6: Offline | J6: =F6/C6 -> 1.2194374
B8: Total | C8: =SUM(C5:C7) -> 57602623 | F8: =SUM(F5:F7) -> 56187821
C10: YoY Growth - Managed properties
C12: April 25 | F12: April 26 | I12: Growth rates
I13: Overall | J13: =F17/C17-1 -> 0.45615207
B14: Short stay | C14: 38426783 | D14: =C14/C17 -> 0.90816256 | F14: 57812035 | G14: =F14/F17 -> 0.93829864 | I14: Short stay | J14: =F14/C14-1 -> 0.5044724
B15: Long stay | C15: 3885887.2 | D15: =C15/C17 -> 0.091837436 | F15: 3801648 | G15: =F15/F17 -> 0.061701359 | I15: Long stay | J15: =F15/C15-1 -> -0.021678241
B17: Total | C17: =SUM(C14:C16) -> 42312671 | F17: =SUM(F14:F16) -> 61613683
C19: MoM Growth - Franchised properties
C21: Feb | E21: March | G21: April (part)
B23: Open | C23: 32945.12 | D23: =C23/C26 -> 0.0075072214 | E23: 222318.82 | F23: =E23/E26 -> 0.041443699 | G23: 210684.72 | H23: =G23/G26 -> 0.036344049
B24: others | C24: =C26-C23 -> 4355512.1 | D24: =C24/C26 -> 0.99249278 | E24: =E26-E23 -> 5142038.7 | F24: =E24/E26 -> 0.9585563 | G24: =G26-G23 -> 5586267.7 | H24: =G24/G26 -> 0.96365595
B26: Total | C26: 4388457.2 | E26: 5364357.5 | G26: 5796952.4

Sheet cashflow
B3: Cashflow - Summary
C4: March '26
C6: Target | D6: Received | I6: To be collected
B7: Inflow | D7: W1 | E7: W2 | F7: W3 | G7: W4 | H7: Total
B8: TA fees | C8: =Inflow!C32 -> 15385400 | D8: =Inflow!E32 -> 0 | E8: =Inflow!F32 -> 70000 | F8: =Inflow!G32 -> 40000 | G8: =Inflow!H32 -> 5040000 | H8: =SUM(D8:G8) -> 5150000 | I8: =C8-SUM(D8:G8) -> 10235400
B9: Management fees | C9: =Inflow!C33 -> 11000000 | D9: =Inflow!E33 -> 355520 | E9: =Inflow!F33 -> 607764 | F9: =Inflow!G33 -> 2608847 | G9: =Inflow!H33 -> 4051004 | H9: =SUM(D9:G9) -> 7623135 | I9: =C9-SUM(D9:G9) -> 3376865
B10: Profit Incentive | C10: =Inflow!C35 -> 500000 | D10: =Inflow!E35 -> 0 | E10: =Inflow!F35 -> 34880 | F10: =Inflow!G35 -> 0 | G10: =Inflow!H35 -> 0 | H10: =SUM(D10:G10) -> 34880 | I10: =C10-SUM(D10:G10) -> 465120
B11: Total | C11: =SUM(C8:C10) -> 26885400 | D11: =SUM(D8:D10) -> 355520 | E11: =SUM(E8:E10) -> 712644 | F11: =SUM(F8:F10) -> 2648847 | G11: =SUM(G8:G10) -> 9091004 | H11: =SUM(D11:G11) -> 12808015 | I11: =SUM(I8:I10) -> 14077385
B12: Outflow - expected for the rest of the month | I12: 11500000
B15: Current bank balance | I15: =SUM(C16:C18) -> 10255000
B16: -Coliving Operations | C16: 6875698
B17: - Coliving | C17: 1431113
B18: -VARS | C18: 1948189
B20: Cash required (Expected outflow - current balance) | I20: =I15-I12 -> -1245000

Sheet Inflow
B4: Cashflow - Breakdown
C5: April
E6: Collections
B7: Inflow | C7: Target | E7: Received | I7: To be collected
B8: 1. TA fees | E8: W1 | F8: W2 | G8: W3 | H8: W4
B9: a) Spark
B10: Spark Ruby, Kolkata | C10: 1800000 | I10: =C10-SUM(E10:H10) -> 1800000
B11: Bengaluru - Spark - Sheshadripuram | C11: 1000000 | I11: =C11-SUM(E11:H11) -> 1000000
B12: Spark Junagad | C12: 825000 | I12: =C12-SUM(E12:H12) -> 825000
B13: Spark Saddahalli ft Nandan | C13: 680400 | I13: =C13-SUM(E13:H13) -> 680400
B14: Tirumala Bypass Road, Tirupati | C14: 1080000 | I14: =C14-SUM(E14:H14) -> 1080000
B15: Andheri - Le Grande | C15: 700000 | I15: =C15-SUM(E15:H15) -> 700000
B16: Spark Rajkot | C16: 800000 | I16: =C16-SUM(E16:H16) -> 800000
I17: =C17-SUM(E17:H17) -> 0
B18: Chakan | C18: 750000 | I18: =C18-SUM(E18:H18) -> 750000
B19: REIT | C19: 5000000 | H19: 5000000 | I19: =C19-SUM(E19:H19) -> 0
B20: Spark Vision Ventures - Tathawade | C20: 1750000 | I20: =C20-SUM(E20:H20) -> 1750000
I21: =C21-SUM(E21:H21) -> 0
B22: b) Olive | C22: =K22+M22 -> 0 | I22: =C22-SUM(E22:H22) -> 0
B23: Olive Jayadeva Hospital | C23: 300000 | I23: =C23-SUM(E23:H23) -> 300000
B24: Banjaara Hills | C24: 150000 | I24: =C24-SUM(E24:H24) -> 150000
B25: Olive Bharatpur | C25: 400000 | I25: =C25-SUM(E25:H25) -> 400000
B26: Olive Kakkanad Info Park | C26: 50000 | F26: 50000 | I26: =C26-SUM(E26:H26) -> 0
I27: =C27-SUM(E27:H27) -> 0
I28: =C28-SUM(E28:H28) -> 0
I29: =C29-SUM(E29:H29) -> 0
B30: c) Open set-up fees | C30: 100000 | E30: 0 | F30: 20000 | G30: 40000 | H30: 40000 | I30: =C30-SUM(E30:H30) -> 0
I31: =C31-SUM(E31:H31) -> 0
B32: Total TA fees | C32: =SUM(C10:C30) -> 15385400 | D32: =SUM(D12:D30) -> 0 | E32: =SUM(E12:E30) -> 0 | F32: =SUM(F12:F30) -> 70000 | G32: =SUM(G12:G30) -> 40000 | H32: =SUM(H12:H30) -> 5040000 | I32: =C32-SUM(E32:H32) -> 10235400
B33: 2. Management fees | C33: =11000000 -> 11000000 | E33: 355520 | F33: 607764 | G33: =3444773+127358-F33-E33 -> 2608847 | H33: =7658015-34880-SUM(E33:G33) -> 4051004 | I33: =C33-SUM(E33:H33) -> 3376865
I34: =C34-SUM(E34:H34) -> 0
B35: 3. Profit Incentive | C35: 500000 | E35: 0 | F35: 34880 | I35: =C35-SUM(E35:H35) -> 465120
I36: =C36-SUM(E36:H36) -> 0
I37: =C37-SUM(E37:H37) -> 0
I38: =C38-SUM(E38:H38) -> 0
B39: Total Inflow | C39: =C32+C33+C35 -> 26885400 | D39: =D32+D33+D35 -> 0 | E39: =E32+E33+E35 -> 355520 | F39: =F32+F33+F35 -> 712644 | G39: =G32+G33+G35 -> 2648847 | H39: =H32+H33+H35 -> 9091004 | I39: =C39-SUM(E39:H39) -> 14077385

Sheet Sheet1
C5: Dairy circle | D5: 400000 | F5: -Salaries | I5: 10600000 | K5: -Salaries | N5: 11000000
C6: hitech | D6: 200000 | F6: -Car EMI | I6: 124266 | K6: -Car EMI | N6: 124266
C7: kundahalli | D7: 300000 | F7: -EE reimbursements | I7: 500000 | K7: -EE reimbursements | N7: 500000
C8: vijawada | D8: =350000*0 -> 0 | F8: -medical insurance | I8: 500000 | K8: -medical insurance | N8: 500000
C9: Vasanth nagar | D9: 350000 | F9: -OPC | I9: 2000000 | K9: -Hisca | N9: 500000
C10: Rajaji nahar | F10: -Rent | I10: 916634.45 | K10: -Zoho | N10: 361000
C11: Domlur | K11: Travel agency | N11: 500000
C12: Meera - Goa | D12: 100000 | K12: -Kingshuk | N12: 200000
C13: Indiranagar | D13: 200000 | I13: =SUM(I5:I12) -> 14640900 | N13: =SUM(N5:N12) -> 13685266
C14: Nivasa | D14: 100000
D16: =SUM(D5:D15) -> 1650000
